hardware_panel.py
hardware_panel-1.0.6.data/data/share/hardware-panel/icons/cpu.svg
hardware_panel-1.0.6.data/data/share/hardware-panel/icons/disk.svg
hardware_panel-1.0.6.data/data/share/hardware-panel/icons/download.svg
hardware_panel-1.0.6.data/data/share/hardware-panel/icons/gpu.svg
hardware_panel-1.0.6.data/data/share/hardware-panel/icons/help.svg
hardware_panel-1.0.6.data/data/share/hardware-panel/icons/ram.svg
hardware_panel-1.0.6.data/data/share/hardware-panel/icons/upload.svg
hardware_panel-1.0.6.dist-info/licenses/LICENSE
modules/__init__.py
modules/hardware_monitor.py
modules/main_window.py
modules/power_manager.py
hardware_panel-1.0.6.dist-info/METADATA
hardware_panel-1.0.6.dist-info/WHEEL
hardware_panel-1.0.6.dist-info/entry_points.txt
hardware_panel-1.0.6.dist-info/top_level.txt
hardware_panel-1.0.6.dist-info/RECORD
