Metadata-Version: 2.4
Name: hardware-panel
Version: 1.0.6
Summary: Powerful system monitoring and hardware control application for Linux.
Home-page: https://github.com/martimmpr/linux-hardware-panel
Author: Martim 'martimmpr' Ribeiro
License: MIT
Project-URL: Bug Tracker, https://github.com/martimmpr/linux-hardware-panel/issues
Project-URL: Source Code, https://github.com/martimmpr/linux-hardware-panel
Project-URL: Changelog, https://github.com/martimmpr/linux-hardware-panel/blob/main/CHANGELOG.md
Classifier: Development Status :: 4 - Beta
Classifier: Intended Audience :: End Users/Desktop
Classifier: Topic :: System :: Monitoring
Classifier: Topic :: System :: Hardware
Classifier: License :: OSI Approved :: MIT License
Classifier: Programming Language :: Python :: 3
Classifier: Programming Language :: Python :: 3.8
Classifier: Programming Language :: Python :: 3.9
Classifier: Programming Language :: Python :: 3.10
Classifier: Programming Language :: Python :: 3.11
Classifier: Operating System :: POSIX :: Linux
Requires-Python: >=3.8
License-File: LICENSE
Requires-Dist: PyQt5>=5.15.0
Requires-Dist: psutil>=5.8.0
Requires-Dist: pyqtgraph>=0.12.0
Dynamic: author
Dynamic: classifier
Dynamic: description
Dynamic: description-content-type
Dynamic: home-page
Dynamic: license
Dynamic: license-file
Dynamic: project-url
Dynamic: requires-dist
Dynamic: requires-python
Dynamic: summary
